imagehat/__init__.py
imagehat/_imagehat.py
imagehat-0.0.28.dist-info/LICENSE
imagehat-0.0.28.dist-info/METADATA
imagehat-0.0.28.dist-info/WHEEL
imagehat-0.0.28.dist-info/top_level.txt
imagehat-0.0.28.dist-info/RECORD
