Metadata-Version: 2.1
Name: imagehat
Version: 0.0.28
Summary: Image HAT
Home-page: UNKNOWN
Author: Richard Waschhauser
License: UNKNOWN
Keywords: Raspberry Pi USB
Platform: UNKNOWN
Classifier: Development Status :: 2 - Pre-Alpha
Classifier: Operating System :: POSIX :: Linux
Classifier: Programming Language :: Python :: 3
Classifier: Programming Language :: Python :: 3.5
Classifier: Programming Language :: Python :: 3.6
Classifier: Programming Language :: Python :: 3.7
Classifier: Programming Language :: Python :: 3.8
Classifier: License :: OSI Approved :: MIT License
Classifier: Topic :: System :: Hardware
Requires-Python: >=3.5
